dankdb/__init__.py
dankdb/dankdb.py
dankdb-0.0.3.dist-info/LICENSE
dankdb-0.0.3.dist-info/METADATA
dankdb-0.0.3.dist-info/WHEEL
dankdb-0.0.3.dist-info/top_level.txt
dankdb-0.0.3.dist-info/RECORD
