Metadata-Version: 2.1
Name: dankdb
Version: 0.0.3
Summary: Easy to use database module
Home-page: https://github.com/DankSideSparkles/DankDB
Author: Hunter Hopper
Author-email: hunterlhopper@gmail.com
License: UNKNOWN
Platform: UNKNOWN
Classifier: License :: OSI Approved :: MIT License
Classifier: Programming Language :: Python :: 3.6
Classifier: Programming Language :: Python :: 3.7
Classifier: Programming Language :: Python :: 3.8
